pyromaths/__init__.py
pyromaths/__main__.py
pyromaths/directories.py
pyromaths/version.py
pyromaths/classes/Fractions.py
pyromaths/classes/Polynome.py
pyromaths/classes/PolynomesCollege.py
pyromaths/classes/Racine.py
pyromaths/classes/SquareRoot.py
pyromaths/classes/Vecteurs.py
pyromaths/classes/__init__.py
pyromaths/cli/__init__.py
pyromaths/cli/dummy.py
pyromaths/data/exercices/img/Arithmetique.png
pyromaths/data/exercices/img/ArrondirNombreDecimal.png
pyromaths/data/exercices/img/BilanTrinomeSansDiscriminant.png
pyromaths/data/exercices/img/CalculMental.png
pyromaths/data/exercices/img/ClasserNombres.png
pyromaths/data/exercices/img/ConstruireZigZag.png
pyromaths/data/exercices/img/Decomposition.png
pyromaths/data/exercices/img/Divisible.png
pyromaths/data/exercices/img/Droites.png
pyromaths/data/exercices/img/EcrireNombreLettre.png
pyromaths/data/exercices/img/EcritureFractionnaire.png
pyromaths/data/exercices/img/EtatStableSysteme2.png
pyromaths/data/exercices/img/Fd1Tangentes.png
pyromaths/data/exercices/img/FractionPartage.png
pyromaths/data/exercices/img/InterpolationMatrices.png
pyromaths/data/exercices/img/LimitesSuites.png
pyromaths/data/exercices/img/MesureAngles.png
pyromaths/data/exercices/img/Operations.png
pyromaths/data/exercices/img/Perpendiculaires.png
pyromaths/data/exercices/img/PlaceVirgule.png
pyromaths/data/exercices/img/PoserDesOperations.png
pyromaths/data/exercices/img/ProduitPuissanceDix.png
pyromaths/data/exercices/img/Proprietes.png
pyromaths/data/exercices/img/QuestionsAbscisses.png
pyromaths/data/exercices/img/Sd1FormeCanonique.png
pyromaths/data/exercices/img/Sd2aRacines.png
pyromaths/data/exercices/img/SymetrieQuadrillage.png
pyromaths/data/exercices/img/TermesDUneSuite.png
pyromaths/data/exercices/img/Vf1SensEtTableau.png
pyromaths/data/exercices/img/Vf2ExtremaGraphiques.png
pyromaths/data/exercices/img/Vf3VariationVersCourbe.png
pyromaths/data/exercices/img/Vf4ComparerImages.png
pyromaths/data/exercices/img/Vf5Extrema_Tableau.png
pyromaths-21.8.2.dist-info/AUTHORS
pyromaths-21.8.2.dist-info/COPYING
pyromaths-21.8.2.dist-info/LICENSE
pyromaths-21.8.2.dist-info/METADATA
pyromaths-21.8.2.dist-info/WHEEL
pyromaths-21.8.2.dist-info/entry_points.txt
pyromaths-21.8.2.dist-info/top_level.txt
pyromaths-21.8.2.dist-info/RECORD
