Metadata-Version: 2.1
Name: pyromaths
Version: 21.8.2
Summary: Create maths exercises in LaTeX and PDF format
Home-page: http://www.pyromaths.org
Author: Jérôme Ortais
Author-email: jerome.ortais@pyromaths.org
License: GPLv3
Download-URL: http://www.pyromaths.org/telecharger/
Project-URL: Documentation, http://pyromaths.readthedocs.org
Project-URL: Download, https://www.pyromaths.org/telecharger/
Project-URL: Forum, https://forum.pyromaths.org
Project-URL: Sources, https://framagit.org/pyromaths/pyromaths
Project-URL: Tickets, https://framagit.org/pyromaths/pyromaths/issues
Project-URL: Version en ligne, https://enligne.pyromaths.org/
Keywords: exercices math latex school
Platform: UNKNOWN
Classifier: Development Status :: 5 - Production/Stable
Classifier: Environment :: Console
Classifier: Intended Audience :: Education
Classifier: License :: OSI Approved :: GNU General Public License v3 (GPLv3)
Classifier: Operating System :: OS Independent
Classifier: Programming Language :: Python
Classifier: Programming Language :: Python :: 3
Classifier: Programming Language :: Python :: 3.5
Classifier: Programming Language :: Python :: 3.7
Classifier: Topic :: Software Development :: Code Generators
Classifier: Topic :: Text Processing :: Markup :: LaTeX
Requires-Dist: jinja2
